odoo/addons/account_move_analytic_recreate/README.rst
odoo/addons/account_move_analytic_recreate/__init__.py
odoo/addons/account_move_analytic_recreate/__manifest__.py
odoo/addons/account_move_analytic_recreate/i18n/account_move_analytic_recreate.pot
odoo/addons/account_move_analytic_recreate/models/__init__.py
odoo/addons/account_move_analytic_recreate/models/account_move.py
odoo/addons/account_move_analytic_recreate/readme/CONTRIBUTORS.rst
odoo/addons/account_move_analytic_recreate/readme/DESCRIPTION.rst
odoo/addons/account_move_analytic_recreate/static/description/icon.png
odoo/addons/account_move_analytic_recreate/static/description/index.html
odoo12_addon_account_move_analytic_recreate-12.0.1.0.0.99.dev2.dist-info/METADATA
odoo12_addon_account_move_analytic_recreate-12.0.1.0.0.99.dev2.dist-info/WHEEL
odoo12_addon_account_move_analytic_recreate-12.0.1.0.0.99.dev2.dist-info/top_level.txt
odoo12_addon_account_move_analytic_recreate-12.0.1.0.0.99.dev2.dist-info/RECORD
